MANIFEST.in
VERSION
setup.py
declarativewidgets/__init__.py
declarativewidgets/extensionapp.py
declarativewidgets/urth_exception.py
declarativewidgets/urth_widget.py
declarativewidgets/widget_channels.py
declarativewidgets/widget_dataframe.py
declarativewidgets/widget_function.py
declarativewidgets/widget_ipw_proxy.py
declarativewidgets/static/bower.json
declarativewidgets/static/declarativewidgets.jar
declarativewidgets/static/urth-widgets.jar
declarativewidgets/static/urth-widgets.tgz
declarativewidgets/static/css/main.css
declarativewidgets/static/docs/docs.build.js
declarativewidgets/static/docs/docs.html
declarativewidgets/static/docs/generated_docs.json
declarativewidgets/static/docs/index.html
declarativewidgets/static/docs/urth-docs.html
declarativewidgets/static/docs/css/index.css
declarativewidgets/static/docs/elements/urth-docs-panel/urth-docs-panel.html
declarativewidgets/static/docs/usage-docs/Basic-Usage.md
declarativewidgets/static/docs/usage-docs/Calling-Functions.md
declarativewidgets/static/docs/usage-docs/Data-Binding.md
declarativewidgets/static/docs/usage-docs/Data-Channels.md
declarativewidgets/static/docs/usage-docs/Data-Visualizations.md
declarativewidgets/static/docs/usage-docs/Serialization-of-data.md
declarativewidgets/static/docs/usage-docs/Using-DataFrames.md
declarativewidgets/static/docs/usage-docs/Utility-Functions.md
declarativewidgets/static/elements/urth-core-behaviors/bower.json
declarativewidgets/static/elements/urth-core-behaviors/dynamic-properties-behavior.html
declarativewidgets/static/elements/urth-core-behaviors/error-display-behavior.html
declarativewidgets/static/elements/urth-core-behaviors/execution-complete-behavior.html
declarativewidgets/static/elements/urth-core-behaviors/jupyter-kernel-observer.html
declarativewidgets/static/elements/urth-core-behaviors/jupyter-notebook-env.html
declarativewidgets/static/elements/urth-core-behaviors/jupyter-persist-behavior.html
jupyter_declarativewidgets.egg-info/PKG-INFO
jupyter_declarativewidgets.egg-info/SOURCES.txt
jupyter_declarativewidgets.egg-info/dependency_links.txt
jupyter_declarativewidgets.egg-info/entry_points.txt
jupyter_declarativewidgets.egg-info/top_level.txt
