Metadata-Version: 1.0
Name: jupyter-declarativewidgets
Version: 0.7.0
Summary: Jupyter extensions for supporting declarative widgets
Home-page: https://github.com/jupyter-incubator/declarativewidgets
Author: Jupyter Development Team
Author-email: jupyter@googlegroups.com
License: BDS
Platform: Jupyter Notebook 4.0.x
